Metadata-Version: 2.1
Name: meu-investimento-thiagonespereira
Version: 0.1
Summary: Uma biblioteca para cálculos de investimentos.
Home-page: https://github.com/thiagonespereira/meu_investimento
Author: Thiago L Pereira
Author-email: tlpereir@gmail.com
License: UNKNOWN
Platform: UNKNOWN
Classifier: Programming Language :: Python :: 3
Classifier: License :: OSI Approved :: MIT License
Classifier: Operating System :: OS Independent
Requires-Python: >=3.6
